beets/__init__.py
beets/__main__.py
beets/autotag/__init__.py
beets/autotag/distance.py
beets/autotag/hooks.py
beets/autotag/match.py
beets/config_default.yaml
beets/dbcore/__init__.py
beets/dbcore/db.py
beets/dbcore/query.py
beets/dbcore/queryparse.py
beets/dbcore/types.py
beets/importer/__init__.py
beets/importer/session.py
beets/importer/stages.py
beets/importer/state.py
beets/importer/tasks.py
beets/library/__init__.py
beets/library/exceptions.py
beets/library/library.py
beets/library/models.py
beets/library/queries.py
beets/logging.py
beets/mediafile.py
beets/metadata_plugins.py
beets/plugins.py
beets/py.typed
beets/test/__init__.py
beets/test/_common.py
beets/test/helper.py
beets/ui/__init__.py
beets/ui/commands/__init__.py
beets/ui/commands/completion.py
beets/ui/commands/completion_base.sh
beets/ui/commands/config.py
beets/ui/commands/fields.py
beets/ui/commands/help.py
beets/ui/commands/import_/__init__.py
beets/ui/commands/import_/display.py
beets/ui/commands/import_/session.py
beets/ui/commands/list.py
beets/ui/commands/modify.py
beets/ui/commands/move.py
beets/ui/commands/remove.py
beets/ui/commands/stats.py
beets/ui/commands/update.py
beets/ui/commands/utils.py
beets/ui/commands/version.py
beets/ui/commands/write.py
beets/util/__init__.py
beets/util/artresizer.py
beets/util/bluelet.py
beets/util/config.py
beets/util/deprecation.py
beets/util/functemplate.py
beets/util/hidden.py
beets/util/id_extractors.py
beets/util/m3u.py
beets/util/pipeline.py
beets/util/units.py
beetsplug/_typing.py
beetsplug/_utils/__init__.py
beetsplug/_utils/art.py
beetsplug/_utils/musicbrainz.py
beetsplug/_utils/requests.py
beetsplug/_utils/vfs.py
beetsplug/absubmit.py
beetsplug/acousticbrainz.py
beetsplug/advancedrewrite.py
beetsplug/albumtypes.py
beetsplug/aura.py
beetsplug/autobpm.py
beetsplug/badfiles.py
beetsplug/bareasc.py
beetsplug/beatport.py
beetsplug/bench.py
beetsplug/bpd/__init__.py
beetsplug/bpd/gstplayer.py
beetsplug/bpm.py
beetsplug/bpsync.py
beetsplug/bucket.py
beets-2.6.0.dist-info/LICENSE
beets-2.6.0.dist-info/METADATA
beets-2.6.0.dist-info/WHEEL
beets-2.6.0.dist-info/entry_points.txt
beets-2.6.0.dist-info/RECORD
