Metadata-Version: 2.1
Name: beets
Version: 2.6.0
Summary: music tagger and library organizer
Home-page: https://beets.io/
License: MIT
Author: Adrian Sampson
Author-email: adrian@radbox.org
Maintainer: Serene-Arc
Requires-Python: >=3.10,<4
Classifier: Environment :: Console
Classifier: Environment :: Web Environment
Classifier: License :: OSI Approved :: MIT License
Classifier: Programming Language :: Python
Classifier: Programming Language :: Python :: 3
Classifier: Programming Language :: Python :: 3.10
Classifier: Programming Language :: Python :: 3.11
Classifier: Programming Language :: Python :: 3.12
Classifier: Programming Language :: Python :: 3.13
Classifier: Programming Language :: Python :: Implementation :: CPython
Classifier: Topic :: Multimedia :: Sound/Audio
Classifier: Topic :: Multimedia :: Sound/Audio :: Players :: MP3
Provides-Extra: absubmit
Provides-Extra: aura
Provides-Extra: autobpm
Provides-Extra: beatport
Provides-Extra: bpd
Provides-Extra: chroma
Provides-Extra: discogs
Provides-Extra: docs
Provides-Extra: embedart
Provides-Extra: embyupdate
Provides-Extra: fetchart
Provides-Extra: import
Provides-Extra: kodiupdate
Provides-Extra: lastgenre
Provides-Extra: lastimport
Provides-Extra: lyrics
Provides-Extra: metasync
Provides-Extra: mpdstats
Provides-Extra: plexupdate
Provides-Extra: reflink
Provides-Extra: replaygain
Provides-Extra: scrub
Provides-Extra: sonosupdate
Provides-Extra: thumbnails
Provides-Extra: titlecase
Provides-Extra: web
Requires-Dist: Pillow ; extra == "aura" or extra == "embedart" or extra == "fetchart" or extra == "thumbnails"
Requires-Dist: PyGObject ; extra == "bpd" or extra == "replaygain"
Requires-Dist: beautifulsoup4 ; extra == "fetchart" or extra == "lyrics"
Requires-Dist: colorama ; sys_platform == "win32"
Requires-Dist: confuse (>=2.1.0)
Requires-Dist: dbus-python ; extra == "metasync"
Requires-Dist: docutils (>=0.20.1) ; extra == "docs"
Requires-Dist: flask ; extra == "aura" or extra == "web"
Requires-Dist: flask-cors ; extra == "aura" or extra == "web"
Requires-Dist: jellyfish
Requires-Dist: langdetect ; extra == "fetchart" or extra == "lyrics"
Requires-Dist: lap (>=0.5.12)
Requires-Dist: librosa (>=0.11) ; extra == "autobpm"
Requires-Dist: mediafile (>=0.12.0)
Requires-Dist: mutagen (>=1.33) ; extra == "scrub"
Requires-Dist: numba (>=0.60) ; python_version < "3.13"
Requires-Dist: numba (>=0.62.1) ; python_version >= "3.13"
Requires-Dist: numpy (>=2.0.2) ; python_version < "3.13"
Requires-Dist: numpy (>=2.3.4) ; python_version >= "3.13"
Requires-Dist: platformdirs (>=3.5.0)
Requires-Dist: py7zr ; extra == "import"
Requires-Dist: pyacoustid ; extra == "chroma"
Requires-Dist: pydata-sphinx-theme ; extra == "docs"
Requires-Dist: pylast ; extra == "lastgenre" or extra == "lastimport"
Requires-Dist: python-mpd2 (>=0.4.2) ; extra == "mpdstats"
Requires-Dist: python3-discogs-client (>=2.3.15) ; extra == "discogs"
Requires-Dist: pyxdg ; extra == "thumbnails"
Requires-Dist: pyyaml
Requires-Dist: rarfile ; extra == "import"
Requires-Dist: reflink ; extra == "reflink"
Requires-Dist: requests (>=2.32.5) ; extra == "absubmit" or extra == "embyupdate" or extra == "fetchart" or extra == "kodiupdate" or extra == "lyrics" or extra == "plexupdate"
Requires-Dist: requests-oauthlib (>=0.6.1) ; extra == "beatport"
Requires-Dist: requests-ratelimiter (>=0.7.0)
Requires-Dist: resampy (>=0.4.3) ; extra == "autobpm"
Requires-Dist: scipy (>=1.13.1) ; python_version < "3.13"
Requires-Dist: scipy (>=1.16.1) ; python_version >= "3.13"
Requires-Dist: soco ; extra == "sonosupdate"
Requires-Dist: sphinx ; extra == "docs"
Requires-Dist: sphinx-copybutton (>=0.5.2) ; extra == "docs"
Requires-Dist: sphinx-design (>=0.6.1) ; extra == "docs"
Requires-Dist: sphinx-toolbox (>=4.1.0) ; extra == "docs"
Requires-Dist: titlecase (>=2.4.1,<3.0.0) ; extra == "titlecase"
Requires-Dist: typing_extensions
Requires-Dist: unidecode (>=1.3.6)
Project-URL: Bug Tracker, https://github.com/beetbox/beets/issues
Project-URL: Changelog, https://github.com/beetbox/beets/blob/master/docs/changelog.rst
Project-URL: Documentation, https://beets.readthedocs.io/en/stable/
Project-URL: Repository, https://github.com/beetbox/beets
